Metadata-Version: 2.1
Name: cltl.asr
Version: 0.0.dev4
Summary: ASR for Leolani
Home-page: https://github.com/leolani/cltl-asr
Author: CLTL
Author-email: t.baier@vu.nl
License: MIT License
Platform: UNKNOWN
Requires-Python: >=3.7
Provides-Extra: impl
Provides-Extra: service
License-File: LICENSE
